pyShicy/__init__.py
pyShicy/__main__.py
pyShicy/decorator.py
pyShicy/exceptions.py
pyShicy/version.py
pyShicy/xd.py
pyShicy/Clients/__init__.py
pyShicy/Clients/client.py
pyShicy/Clients/pytgcalls.py
pyShicy/Clients/startup.py
pyShicy/dB/__init__.py
pyShicy/dB/_core.py
pyShicy/dB/afk_db.py
pyShicy/dB/antiflood_db.py
pyShicy/dB/asst_fns.py
pyShicy/dB/asstcmd_db.py
pyShicy/dB/autoban_db.py
pyShicy/dB/blacklist_chat_db.py
pyShicy/dB/blacklist_db.py
pyShicy/dB/botchat_db.py
pyShicy/dB/ch_db.py
pyShicy/dB/clients.py
pyShicy/dB/echo_db.py
pyShicy/dB/filestore_db.py
pyShicy/dB/filter_db.py
pyShicy/dB/forcesub_db.py
pyShicy/dB/gban_mute_db.py
pyShicy/dB/gcast_blacklist_db.py
pyShicy/dB/greetings_db.py
pyShicy/dB/logusers_db.py
pyShicy/dB/mute_db.py
pyShicy/dB/night_db.py
pyShicy/dB/notes_db.py
pyShicy/dB/nsfw_db.py
pyShicy/dB/pmpermit_db.py
pyShicy/dB/snips_db.py
pyShicy/dB/vc_sudos.py
pyShicy/dB/warn_db.py
pyShicy/methods/__init__.py
pyShicy/methods/_database.py
pyShicy/methods/_misc.py
pyShicy/methods/changer.py
pyShicy/methods/converter.py
pyShicy/methods/func.py
pyShicy/methods/funcb.py
pyShicy/methods/helpers.py
pyShicy/methods/hosting.py
pyShicy/methods/inlinebot.py
pyShicy/methods/queue.py
pyShicy/methods/thumbnail.py
pyShicy/pyrogram/__init__.py
pyShicy/pyrogram/_wrappers.py
pyShicy/pyrogram/func.py
pyShicy/pyrogram/misc.py
pyShicy/pyrogram/pastebin.py
pyShicy/pyrogram/sections.py
pyShicy/pyrogram/toolbot.py
pyShicy/pyrogram/tools.py
pyShicy/resources/__init__.py
pyShicy/telethon/__init__.py
pyShicy/telethon/dB/__init__.py
pyShicy/telethon/dB/_core.py
pyShicy/telethon/dB/afk_db.py
pyShicy/telethon/dB/antiflood_db.py
pyShicy/telethon/dB/asst_fns.py
pyShicy/telethon/dB/asstcmd_db.py
pyShicy/telethon/dB/autoban_db.py
pyShicy/telethon/dB/blacklist_chat_db.py
pyShicy/telethon/dB/blacklist_db.py
pyShicy/telethon/dB/botchat_db.py
pyShicy/telethon/dB/broadcast_db.py
pyShicy/telethon/dB/ch_db.py
pyShicy/telethon/dB/clients.py
pyShicy/telethon/dB/dnd_db.py
pyShicy-0.1.7.dist-info/LICENSE
pyShicy-0.1.7.dist-info/METADATA
pyShicy-0.1.7.dist-info/NOTICE
pyShicy-0.1.7.dist-info/WHEEL
pyShicy-0.1.7.dist-info/top_level.txt
pyShicy-0.1.7.dist-info/RECORD
