Metadata-Version: 2.1
Name: pyShicy
Version: 0.1.7
Summary: A Secure and Powerful Python-Telethon Based and Python-Pyrogram Based Library For Your Userbot Module.
Home-page: https://github.com/sip-userbot/sip-userbot
Author: sip-userbot
Author-email: sipuserbot@gmail.com
License: GNU General Public License v3.0 (GPL-3.0)
Project-URL: Bug Tracker, https://github.com/sip-userbot/sip-userbot/issues
Project-URL: Source Code, https://github.com/sip-userbot/sip-userbot
Classifier: Programming Language :: Python :: 3
Classifier: Programming Language :: Python :: 3.8
Classifier: Programming Language :: Python :: 3.9
Classifier: Programming Language :: Python :: 3.10
Classifier: Programming Language :: Python :: 3.11
Classifier: License :: OSI Approved :: GNU General Public License v3 (GPLv3)
Classifier: Operating System :: OS Independent
Requires-Python: ~=3.7
License-File: LICENSE
License-File: NOTICE
Requires-Dist: aiohttp
Requires-Dist: asyncio
Requires-Dist: fipper
Requires-Dist: gitpython
Requires-Dist: pymediainfo
Requires-Dist: python-decouple
Requires-Dist: python-dotenv
Requires-Dist: pyrogram (==1.4.16)
Requires-Dist: requests
Requires-Dist: telethon (==1.24.0)
Requires-Dist: tgcrypto
Requires-Dist: tracemoepy
Requires-Dist: urllib3
